Metadata-Version: 2.1
Name: odoo14-addon-dms-field
Version: 14.0.1.0.1
Summary: Create DMS View and allow to use them inside a record
Home-page: https://github.com/OCA/dms
Author: Creu Blanca,Odoo Community Association (OCA)
Author-email: support@odoo-community.org
License: LGPL-3
Platform: UNKNOWN
Classifier: Programming Language :: Python
Classifier: Framework :: Odoo
Classifier: Framework :: Odoo :: 14.0
Classifier: License :: OSI Approved :: GNU Lesser General Public License v3 (LGPLv3)
Requires-Python: >=3.6
Requires-Dist: odoo14-addon-dms
Requires-Dist: odoo <14.1dev,>=14.0a
